{
  "schema_version": 1,
  "generated_at": "2026-05-04T16:23:22Z",
  "date": "2026-05-04",
  "username": "roperev",
  "host": "github.com",
  "token_source": "public_events",
  "days": 7,
  "repos_considered": [
    {
      "full_name": "aemdemos/poc-vyepti",
      "source": "public_events"
    },
    {
      "full_name": "aemsites/idfc",
      "source": "public_events"
    }
  ],
  "runs": [
    {
      "full_name": "aemdemos/poc-vyepti",
      "status": "ok",
      "html_path": "reports/team/roperev-aemdemos-poc-vyepti-2026-05-04.html",
      "rate_limit_remaining": 4743
    },
    {
      "full_name": "aemsites/idfc",
      "status": "ok",
      "html_path": "reports/team/roperev-aemsites-idfc-2026-05-04.html",
      "rate_limit_remaining": 4655
    }
  ],
  "summary": {
    "ok": 2,
    "error": 0,
    "skipped": 0
  }
}